README.md
setup.py
nbpdfexport/__init__.py
nbpdfexport/bundler.py
nbpdfexport.egg-info/PKG-INFO
nbpdfexport.egg-info/SOURCES.txt
nbpdfexport.egg-info/dependency_links.txt
nbpdfexport.egg-info/entry_points.txt
nbpdfexport.egg-info/requires.txt
nbpdfexport.egg-info/top_level.txt