Metadata-Version: 1.2
Name: nbpdfexport
Version: 0.1
Summary: Convert Jupyter Notebooks to PDF without LaTeX
Home-page: http://github.com/yuvipanda/nbpdfexport
Author: Yuvi Panda
Author-email: yuvipanda@gmail.com
License: BSD
Platform: UNKNOWN
Requires-Python: >=3.6
